{
    "id" : "io.github.vmkspv.netsleuth",
    "runtime" : "org.gnome.Platform",
    "runtime-version" : "49",
    "sdk" : "org.gnome.Sdk",
    "command" : "netsleuth",
    "finish-args" : [
        "--share=ipc",
        "--socket=wayland",
        "--socket=fallback-x11",
        "--device=dri",
        "--own-name=io.github.vmkspv.netsleuth.SearchProvider"
    ],
    "modules" : [
        {
            "name" : "netsleuth",
            "buildsystem" : "meson",
            "sources" : [
                {
                    "type" : "dir",
                    "path" : "."
                }
            ]
        }
    ]
}